easyterm/__init__.py
easyterm/colorprint.py
easyterm/commandlineopt.py
easyterm/commandutils.py
easyterm-1.0.1.dist-info/LICENSE
easyterm-1.0.1.dist-info/METADATA
easyterm-1.0.1.dist-info/WHEEL
easyterm-1.0.1.dist-info/top_level.txt
easyterm-1.0.1.dist-info/RECORD
