Metadata-Version: 2.1
Name: easyterm
Version: 1.0.1
Summary: convenient python functions for everyday use of terminal
Home-page: https://github.com/marco-mariotti/easyterm
Author: Marco Mariotti
Author-email: marco.mariotti@ub.edu
Classifier: Programming Language :: Python :: 3
Classifier: License :: OSI Approved :: MIT License
Classifier: Operating System :: OS Independent
Requires-Python: >=3.6
License-File: LICENSE
